opt_einsum_torch/__init__.py
opt_einsum_torch/einsum.py
opt_einsum_torch/planner.py
opt_einsum_torch/utils.py
opt_einsum_torch-0.1.0.dist-info/LICENSE
opt_einsum_torch-0.1.0.dist-info/METADATA
opt_einsum_torch-0.1.0.dist-info/WHEEL
opt_einsum_torch-0.1.0.dist-info/top_level.txt
opt_einsum_torch-0.1.0.dist-info/RECORD
