Metadata-Version: 2.1
Name: opt-einsum-torch
Version: 0.1.0
Summary: Memory-efficient optimum einsum using opt_einsum planning and PyTorch kernels.
Home-page: http://github.com/hhaoyan/opt-einsum-torch
Author: Haoyan Huo
Author-email: hhaoyann@gmail.com
License: MIT
Platform: UNKNOWN
Classifier: Environment :: GPU
Classifier: Programming Language :: Python :: 3.6
Classifier: Programming Language :: Python :: 3 :: Only
Classifier: Development Status :: 1 - Planning
Classifier: Intended Audience :: Science/Research
Classifier: License :: OSI Approved :: MIT License
Classifier: Operating System :: OS Independent
Classifier: Topic :: Software Development :: Libraries :: Python Modules
Requires-Python: >=3.6
License-File: LICENSE
Requires-Dist: humanize
Requires-Dist: numpy
Requires-Dist: opt-einsum
Requires-Dist: torch
